plover_uinput/__init__.py
plover_uinput/all_keys.py
plover_uinput/keys.py
plover_uinput/symbols.py
plover_uinput-0.0.13.dist-info/LICENSE
plover_uinput-0.0.13.dist-info/METADATA
plover_uinput-0.0.13.dist-info/WHEEL
plover_uinput-0.0.13.dist-info/entry_points.txt
plover_uinput-0.0.13.dist-info/top_level.txt
plover_uinput-0.0.13.dist-info/RECORD
