Metadata-Version: 2.1
Name: plover-uinput
Version: 0.0.13
Summary: Plover output plugin for linux using evdev / uinput
Home-page: https://github.com/LilleAila/plover-uinput
Author: LilleAila
License: MIT
Keywords: plover plover_plugin
Requires-Python: >=3.8
License-File: LICENSE
Requires-Dist: plover >=4.0.0rc2
Requires-Dist: evdev >=1.7.0
Requires-Dist: xkbcommon >=0.8
